keyguardian/__init__.py
keyguardian/cli.py
keyguardian/core.py
keyguardian/encryption.py
keyguardian-0.1.2.dist-info/LICENSE
keyguardian-0.1.2.dist-info/METADATA
keyguardian-0.1.2.dist-info/WHEEL
keyguardian-0.1.2.dist-info/entry_points.txt
keyguardian-0.1.2.dist-info/top_level.txt
keyguardian-0.1.2.dist-info/RECORD
