Metadata-Version: 2.1
Name: keyguardian
Version: 0.1.2
Summary: A Python package for securely generating and managing encryption keys.
Home-page: https://github.com/krishnaagarwal781/mask_keys_server
Author: Krishna Agarwal
Author-email: krishnacool781@gmail.com
Classifier: Programming Language :: Python :: 3
Classifier: License :: OSI Approved :: MIT License
Classifier: Operating System :: OS Independent
Requires-Python: >=3.6
License-File: LICENSE
Requires-Dist: requests
Requires-Dist: python-dotenv
